{"Academia":"expense","Alimentação":"expense","Alimentação:Restaurante":"expense","Alimentação:Supermercado":"expense","Aulas":"expense","Ações":"income","Cachorros":"expense","Carro":"expense","Carro:Combustível":"expense","Carro:Estacionamento":"expense","Carro:Oficina":"expense","Carro:Seguro":"expense","Carro:Sem Parar":"expense","Carro:Tributos Carro":"expense","Carro:Troca Carro":"expense","Carro:Uber":"expense","Casa":"expense","Casa:Casa":"expense","Casa:Casa Alpha":"expense","Casa:Decoração Casa":"expense","Categoria":"expense","Contas":"expense","Despesas Reembolsáveis":"expense","Diversos":"expense","Doação":"expense","Educação":"expense","Empregada":"expense","Estética":"expense","Filhos":"expense","Imposto de Renda":"expense","Lazer":"expense","Outras Rendas":"income","Presentes":"expense","Renda Financeira":"income","Roupas":"expense","Salário":"income","Saúde:Diversos Saúde":"expense","Saúde:Farmácia":"expense","Saúde:Médicos":"expense","Saúde:Reembolso Seguro":"expense","Saúde:Seguro Saúde":"expense","Tarifas":"expense","Viagens":"expense","Viagens:Alimentação":"expense","Viagens:Atrações":"expense","Viagens:Compras":"expense","Viagens:Diversos":"expense","Viagens:Hotel":"expense","Viagens:IOF":"expense","Viagens:Transporte":"expense"}